StudentScore/__init__.py
StudentScore/__main__.py
StudentScore/conversion.py
StudentScore/result_schema.json
StudentScore/schema.py
StudentScore/score.py
StudentScore/version.py
StudentScore/yaml.py
studentscore-0.6.0.dist-info/METADATA
studentscore-0.6.0.dist-info/WHEEL
studentscore-0.6.0.dist-info/entry_points.txt
studentscore-0.6.0.dist-info/licenses/LICENSE.txt
studentscore-0.6.0.dist-info/RECORD
