Metadata-Version: 2.4
Name: StudentScore
Version: 0.6.0
Summary: Computing score of a given student assignment
License: MIT
License-File: LICENSE.txt
Keywords: testing,functional-testing
Author: Yves Chevallier
Author-email: yves.chevallier@heig-vd.ch
Requires-Python: >=3.10,<4.0
Classifier: Development Status :: 3 - Alpha
Classifier: Environment :: Console
Classifier: Intended Audience :: Developers
Classifier: Intended Audience :: Education
Classifier: Intended Audience :: Science/Research
Classifier: License :: OSI Approved :: MIT License
Classifier: Operating System :: MacOS :: MacOS X
Classifier: Operating System :: Microsoft :: Windows
Classifier: Operating System :: OS Independent
Classifier: Operating System :: POSIX
Classifier: Programming Language :: Python
Classifier: Programming Language :: Python :: 3
Classifier: Programming Language :: Python :: 3.10
Classifier: Programming Language :: Python :: 3.11
Classifier: Programming Language :: Python :: 3.12
Classifier: Programming Language :: Python :: 3.13
Classifier: Programming Language :: Python :: 3.14
Classifier: Topic :: Scientific/Engineering
Classifier: Topic :: Software Development :: Libraries
Provides-Extra: dev
Provides-Extra: test
Requires-Dist: click (>=8.0.0)
Requires-Dist: colorama (>=0.4.0)
Requires-Dist: pydantic (>=2.7,<3.0)
Requires-Dist: pyyaml (>=6.0)
Requires-Dist: typer (>=0.12,<1.0)
Project-URL: Bug Tracker, https://github.com/heig-tin-info/score/issues
Project-URL: Documentation, https://heig-tin-info.github.io/score/
Project-URL: Homepage, https://github.com/heig-tin-info/score
Project-URL: Repository, https://github.com/heig-tin-info/score
